.mina/core.toml
satori/__init__.py
satori/_vendor/fleep.py
satori/const.py
satori/element.py
satori/event.py
satori/exception.py
satori/model.py
satori/parser.py
satori/utils.py
satori_python_core-0.17.7.dist-info/METADATA
satori_python_core-0.17.7.dist-info/WHEEL
satori_python_core-0.17.7.dist-info/licenses/LICENSE
satori_python_core-0.17.7.dist-info/RECORD
